{
  "feature_columns": [
    "Batch_ID",
    "Flour_kg_mean",
    "Flour_kg_max",
    "Flour_kg_num_valleys",
    "Sugar_kg_mean",
    "Sugar_kg_std",
    "Sugar_kg_min",
    "Sugar_kg_max",
    "Sugar_kg_median",
    "Sugar_kg_range",
    "Sugar_kg_q25",
    "Sugar_kg_q75",
    "Sugar_kg_iqr",
    "Sugar_kg_cv",
    "Sugar_kg_trend_slope",
    "Sugar_kg_trend_r2",
    "Yeast_kg_trend_pvalue",
    "Salt_kg_iqr",
    "Salt_kg_kurtosis",
    "Salt_kg_trend_r2",
    "Water_Temp_C_iqr",
    "Water_Temp_C_kurtosis",
    "Water_Temp_C_trend_r2",
    "Water_Temp_C_num_peaks",
    "Water_Temp_C_num_valleys",
    "Mixer_Speed_RPM_std",
    "Mixer_Speed_RPM_min",
    "Mixer_Speed_RPM_range",
    "Mixer_Speed_RPM_iqr",
    "Mixer_Speed_RPM_cv",
    "Mixer_Speed_RPM_num_valleys",
    "Mixing_Temp_C_num_peaks",
    "Fermentation_Temp_C_range",
    "Fermentation_Temp_C_skewness",
    "Fermentation_Temp_C_num_peaks",
    "Fermentation_Temp_C_num_valleys",
    "Oven_Temp_C_skewness",
    "Oven_Temp_C_num_valleys",
    "Oven_Humidity_pct_num_peaks",
    "Oven_Humidity_pct_num_valleys",
    "time_steps",
    "rpm_per_kg_flour",
    "Flour_kg_mean_deviation",
    "Sugar_kg_mean_deviation",
    "Sugar_kg_deviation_std",
    "Salt_kg_max_deviation",
    "Mixer_Speed_RPM_deviation_std",
    "Sugar_kg_volatility",
    "Mixer_Speed_RPM_mean_change_rate",
    "Mixer_Speed_RPM_volatility",
    "Fermentation_Temp_C_mean_change_rate"
  ],
  "target_columns": [
    "Final_Weight",
    "Quality_Score"
  ],
  "training_timestamp": "20250824_065830",
  "validation_results": {
    "XGBoost": {
      "passed": 